mcp_server_memos/__init__.py
mcp_server_memos/__main__.py
mcp_server_memos/config.py
mcp_server_memos/server.py
mcp_server_memos/proto_gen/__init__.py
mcp_server_memos/proto_gen/google/__init__.py
mcp_server_memos/proto_gen/google/api/__init__.py
mcp_server_memos/proto_gen/memos/__init__.py
mcp_server_memos/proto_gen/memos/api/__init__.py
mcp_server_memos/proto_gen/memos/api/v1/__init__.py
iflow_mcp_mcp_server_memos-0.1.15.dist-info/METADATA
iflow_mcp_mcp_server_memos-0.1.15.dist-info/WHEEL
iflow_mcp_mcp_server_memos-0.1.15.dist-info/entry_points.txt
iflow_mcp_mcp_server_memos-0.1.15.dist-info/licenses/LICENSE
iflow_mcp_mcp_server_memos-0.1.15.dist-info/RECORD
