Metadata-Version: 2.4
Name: iflow-mcp_mcp-server-memos
Version: 0.1.15
Summary: Add your description here
Project-URL: Repository, https://github.com/RyoJerryYu/mcp-server-memos-py
License: MIT License
License-File: LICENSE
Classifier: Development Status :: 3 - Alpha
Classifier: Intended Audience :: Developers
Classifier: License :: OSI Approved :: MIT License
Classifier: Programming Language :: Python :: 3
Classifier: Programming Language :: Python :: 3.12
Classifier: Programming Language :: Python :: 3.13
Requires-Python: >=3.12
Requires-Dist: betterproto[compiler]>=2.0.0b6
Requires-Dist: grpclib>=0.4.7
Requires-Dist: mcp>=1.1.0
Requires-Dist: pydantic>=2.10.3
